yalesmartalarmclient/__init__.py
yalesmartalarmclient/auth.py
yalesmartalarmclient/client.py
yalesmartalarmclient/const.py
yalesmartalarmclient/exceptions.py
yalesmartalarmclient/lock.py
yalesmartalarmclient/py.typed
yalesmartalarmclient-0.4.2.dist-info/LICENSE
yalesmartalarmclient-0.4.2.dist-info/METADATA
yalesmartalarmclient-0.4.2.dist-info/WHEEL
yalesmartalarmclient-0.4.2.dist-info/RECORD
