Metadata-Version: 2.1
Name: yalesmartalarmclient
Version: 0.4.2
Summary: Interact with Yale Smart Alarm systems
Home-page: https://github.com/domwillcode/yale-smart-alarm-client
License: Apache-2.0
Keywords: alarm,Yale,Smart Alarm
Author: Dominic Willson
Author-email: domwillcode@gmail.com
Maintainer: G Johansson
Maintainer-email: goran.johansson@shiftit.se
Requires-Python: >=3.11,<4.0
Classifier: Development Status :: 5 - Production/Stable
Classifier: Intended Audience :: Developers
Classifier: License :: OSI Approved :: Apache Software License
Classifier: Natural Language :: English
Classifier: Programming Language :: Python :: 3
Classifier: Programming Language :: Python :: 3.11
Classifier: Programming Language :: Python :: 3.12
Classifier: Topic :: Software Development :: Libraries :: Python Modules
Requires-Dist: requests (>=2.32.0,<3.0.0)
Project-URL: Bug Tracker, https://github.com/domwillcode/yale-smart-alarm-client/issues
Project-URL: Changelog, https://github.com/domwillcode/yale-smart-alarm-client/releases
Project-URL: Documentation, https://github.com/domwillcode/yale-smart-alarm-client
Project-URL: Repository, https://github.com/domwillcode/yale-smart-alarm-client
